killproc
