Metadata-Version: 1.0
Name: killproc
Version: 1.0.1
Summary: Kill unix processes by name
Home-page: https://github.com/jfischer/killproc
Author: Jeff Fischer
Author-email: jeffrey.fischer@genforma.com
License: Apache V2.0
Platform: UNKNOWN
Classifier: Environment :: Console
Classifier: License :: OSI Approved :: Apache Software License
Classifier: Operating System :: POSIX
Classifier: Topic :: System :: Systems Administration
